{
	"Devices":	[{
			"ID":	0,
			"SerialNumber":	"DS-2CD1023G0E-I(L)20210203AAWRF46862142",
			"ChannelNumber":	1,
			"StartChannel":	1,
			"AlarmInNum":	0,
			"AlarmOutNum":	0,
			"IPChanNum":	0,
			"MirrorChanNum":	0,
			"StartMirrorChanNo":	0,
			"LocalNodeName":	"192.168.60.4",
			"DeviceType":	31,
			"DiskNum":	0,
			"LoginUserName":	"admin",
			"LoginUserPwd":	"abcd1234",
			"DeviceIP":	"192.168.60.105",
			"DeviceMultiIP":	"0.0.0.0",
			"DevicePort":	8000,
			"DeviceName":	"DS-2CD1023G0E-I(L)",
			"LoginMode":	0,
			"Https":	0,
			"Channels":	[{
					"ChanID":	0,
					"DeviceIndex":	0,
					"ChanIndex":	0,
					"ChanName":	"Camera1",
					"Protocol":	0,
					"PicResolution":	0,
					"PicQuality":	0,
					"Enable":	1,
					"PreviewMode":	0,
					"PreviewProtocolType":	0,
					"VideoCodingType":	0,
					"StreamType":	0,
					"LinkMode":	0
				}]
		}, {
			"ID":	1,
			"SerialNumber":	"DS-2CD1023G0E-I(L)20210203AAWRF46862142",
			"ChannelNumber":	1,
			"StartChannel":	1,
			"AlarmInNum":	0,
			"AlarmOutNum":	0,
			"IPChanNum":	0,
			"MirrorChanNum":	0,
			"StartMirrorChanNo":	0,
			"LocalNodeName":	"192.168.2.1",
			"DeviceType":	31,
			"DiskNum":	0,
			"LoginUserName":	"admin",
			"LoginUserPwd":	"abcd1234",
			"DeviceIP":	"192.168.2.247",
			"DeviceMultiIP":	"0.0.0.0",
			"DevicePort":	8000,
			"DeviceName":	"DS-2CD1023G0E-I(L)",
			"LoginMode":	0,
			"Https":	0,
			"Channels":	[{
					"ChanID":	0,
					"DeviceIndex":	1,
					"ChanIndex":	0,
					"ChanName":	"Camera1",
					"Protocol":	0,
					"PicResolution":	0,
					"PicQuality":	0,
					"Enable":	1,
					"PreviewMode":	0,
					"PreviewProtocolType":	0,
					"VideoCodingType":	0,
					"StreamType":	0,
					"LinkMode":	0
				}]
		}, {
			"ID":	2,
			"SerialNumber":	"DS-2CD1023G0E-I(L)20210203AAWRF46862142",
			"ChannelNumber":	1,
			"StartChannel":	1,
			"AlarmInNum":	0,
			"AlarmOutNum":	0,
			"IPChanNum":	0,
			"MirrorChanNum":	0,
			"StartMirrorChanNo":	0,
			"LocalNodeName":	"192.168.2.1",
			"DeviceType":	31,
			"DiskNum":	0,
			"LoginUserName":	"admin",
			"LoginUserPwd":	"abcd1234",
			"DeviceIP":	"192.168.2.11",
			"DeviceMultiIP":	"0.0.0.0",
			"DevicePort":	8000,
			"DeviceName":	"DS-2CD1023G0E-I(L)",
			"LoginMode":	0,
			"Https":	0,
			"Channels":	[{
					"ChanID":	0,
					"DeviceIndex":	2,
					"ChanIndex":	0,
					"ChanName":	"Camera1",
					"Protocol":	0,
					"PicResolution":	0,
					"PicQuality":	0,
					"Enable":	1,
					"PreviewMode":	0,
					"PreviewProtocolType":	0,
					"VideoCodingType":	0,
					"StreamType":	0,
					"LinkMode":	0
				}]
		}]
}